graph_state_generation/__init__.py
graph_state_generation/old_code/visualize_result.py
graph_state_generation/optimizers/__init__.py
graph_state_generation/optimizers/node_to_patch_mapper.py
graph_state_generation/optimizers/pre_mapping_optimizer.py
graph_state_generation/optimizers/stabilizer_measurement_scheduler.py
graph_state_generation/substrate_scheduler/__init__.py
graph_state_generation/substrate_scheduler/substrate_scheduler_two_row.py
graph_state_generation/utility/__init__.py
graph_state_generation/utility/constant.py
graph_state_generation/visualization_tools/__init__.py
graph_state_generation/visualization_tools/ascii_visualizer.py
graph_state_generation-0.2.0.dist-info/LICENSE
graph_state_generation-0.2.0.dist-info/METADATA
graph_state_generation-0.2.0.dist-info/WHEEL
graph_state_generation-0.2.0.dist-info/top_level.txt
graph_state_generation-0.2.0.dist-info/RECORD
