Metadata-Version: 2.1
Name: graph-state-generation
Version: 0.2.0
Summary: "Graph State Generation"
Home-page: https://github.com/sfc-aqua/gosc-graph-state-generation
Author: Aqua
Author-email: sitong@sfc.wide.ad.jp,
License: MIT
Classifier: Programming Language :: Python :: 3
Classifier: Operating System :: OS Independent
Classifier: License :: OSI Approved :: Apache Software License
Classifier: Topic :: Scientific/Engineering
Requires-Python: ~=3.8
License-File: LICENSE
Requires-Dist: networkx (==2.8.7)
Requires-Dist: matplotlib
Requires-Dist: numpy (>=1.20)
Provides-Extra: dev
Requires-Dist: black (~=22.3) ; extra == 'dev'
Requires-Dist: flake8 (~=3.9.0) ; extra == 'dev'
Requires-Dist: Flake8-pyproject (>=0.9.0) ; extra == 'dev'
Requires-Dist: isort (~=5.9.0) ; extra == 'dev'
Requires-Dist: mypy (~=0.910) ; extra == 'dev'
Requires-Dist: pytest (~=6.2) ; extra == 'dev'
Requires-Dist: pytest-cov (>=2.12) ; extra == 'dev'
